{"cameraMode":{"drawMode":0,"name":"Shaded","section":"Shading Mode"},"sceneLighting":true,"audioPlay":false,"sceneViewState":{"m_AlwaysRefresh":false,"showFog":true,"showSkybox":true,"showFlares":true,"showImageEffects":true,"showParticleSystems":true,"showVisualEffectGraphs":true,"m_FxEnabled":true},"in2DMode":false,"pivot":{"x":7.159693717956543,"y":-31.583738327026368,"z":8.574457168579102},"rotation":{"x":0.5332226157188416,"y":0.3203057050704956,"z":-0.22823947668075562,"w":0.7487130761146545},"size":18.05425262451172,"orthographic":false}